{
  "collapse-filter": false,
  "search": "",
  "showTags": false,
  "showAttachments": true,
  "hideUnresolved": false,
  "showOrphans": true,
  "collapse-color-groups": true,
  "colorGroups": [],
  "collapse-display": false,
  "showArrow": false,
  "textFadeMultiplier": -0.6,
  "nodeSizeMultiplier": 1.92088686652391,
  "lineSizeMultiplier": 1,
  "collapse-forces": false,
  "centerStrength": 0.518713248970312,
  "repelStrength": 12.1145610278373,
  "linkStrength": 1,
  "linkDistance": 389,
  "scale": 0.5087618855792623,
  "close": true
}